AUTHORS
LICENSE
MANIFEST.in
README.md
setup.cfg
setup.py
mathchem/__init__.py
mathchem/all.py
mathchem/mathchem.py
mathchem/utilities.py
mathchem.egg-info/PKG-INFO
mathchem.egg-info/SOURCES.txt
mathchem.egg-info/dependency_links.txt
mathchem.egg-info/requires.txt
mathchem.egg-info/top_level.txt
tests/__init__.py
tests/test.py