Metadata-Version: 1.1
Name: mathchem
Version: 1.0.7
Summary: UNKNOWN
Home-page: https://github.com/hamster3d/mathchem-package
Author: Alexander Vasilyev
Author-email: hamster3d@gmail.com
License: MIT
Platform: UNKNOWN
Classifier: Development Status :: 3 - Alpha
Classifier: Environment :: Console
Classifier: Intended Audience :: Science/Research
Classifier: License :: OSI Approved :: MIT License
Classifier: Operating System :: OS Independent
Classifier: Programming Language :: Python
